ml_tuning/__init__.py
ml_tuning/exceptions.py
ml_tuning/kNN_tuning.py
ml_tuning/test.py
ml_tuning-0.0.1.dist-info/LICENSE
ml_tuning-0.0.1.dist-info/METADATA
ml_tuning-0.0.1.dist-info/WHEEL
ml_tuning-0.0.1.dist-info/top_level.txt
ml_tuning-0.0.1.dist-info/RECORD
