Metadata-Version: 2.1
Name: ml-tuning
Version: 0.0.1
Summary: Tuning some machine learning function parameters
Home-page: https://github.com/Eajay/ml_tuning
Author: Yijiang Zheng
Author-email: yijiang_zheng@outlook.com
License: MIT
Download-URL: https://github.com/Eajay/ml_tuning.git
Platform: UNKNOWN
Classifier: Development Status :: 3 - Alpha
Classifier: Programming Language :: Python :: 3
Classifier: Intended Audience :: Developers
Classifier: License :: OSI Approved :: MIT License
Classifier: Operating System :: OS Independent
Requires-Python: >=3.6
